workframe/__init__.py
workframe/core.py
workframe/crud.py
workframe/forms/__init__.py
workframe/forms/generator.py
workframe/models/__init__.py
workframe/models/field.py
workframe/models/models.py
workframe/models/table.py
workframe/models/user.py
workframe/static/css/workframe.css
workframe/static/js/workframe.js
workframe/templates/base.html
workframe/templates/dashboard.html
workframe/templates/admin/user_detail_with_groups.html
workframe/templates/auth/change_password.html
workframe/templates/auth/edit_profile.html
workframe/templates/auth/login.html
workframe/templates/auth/profile.html
workframe/templates/crud/detail.html
workframe/templates/crud/form.html
workframe/templates/crud/linked.html
workframe/templates/crud/list.html
workframe/templates/crud/manytomany.html
workframe/templates/errors/404.html
workframe/templates/errors/500.html
workframe/templates/errors/error.html
workframe/views/__init__.py
workframe/views/auth.py
workframe/views/detail.py
workframe/views/linked_module.py
workframe/views/list.py
workframe/views/manytomany_module.py
workframe/views/module.py
workframe/views/user_management_module.py
workframe-0.1.2.dist-info/licenses/LICENSE
workframe-0.1.2.dist-info/METADATA
workframe-0.1.2.dist-info/WHEEL
workframe-0.1.2.dist-info/top_level.txt
workframe-0.1.2.dist-info/RECORD
