Metadata-Version: 2.4
Name: workframe
Version: 0.1.2
Summary: Simple Flask-based framework for building business applications quickly
Home-page: https://github.com/massyn/workframe
Author: WorkFrame Contributors
Author-email: WorkFrame Contributors <workframe@example.com>
Maintainer-email: WorkFrame Contributors <workframe@example.com>
License: MIT
Project-URL: Homepage, https://github.com/massyn/workframe/
Project-URL: Documentation, https://github.com/massyn/workframe/
Project-URL: Repository, https://github.com/massyn/workframe/
Project-URL: Bug Tracker, https://github.com/massyn/workframe/issues
Keywords: flask,framework,business,crud,web,application
Classifier: Development Status :: 4 - Beta
Classifier: Intended Audience :: Developers
Classifier: License :: OSI Approved :: MIT License
Classifier: Programming Language :: Python :: 3
Classifier: Programming Language :: Python :: 3.9
Classifier: Programming Language :: Python :: 3.10
Classifier: Programming Language :: Python :: 3.11
Classifier: Programming Language :: Python :: 3.12
Classifier: Framework :: Flask
Classifier: Topic :: Internet :: WWW/HTTP :: Dynamic Content
Classifier: Topic :: Software Development :: Libraries :: Python Modules
Classifier: Topic :: Office/Business
Requires-Python: >=3.9
License-File: LICENSE
Requires-Dist: Flask>=2.3.0
Requires-Dist: Flask-SQLAlchemy>=3.0.0
Requires-Dist: Flask-Login>=0.6.0
Requires-Dist: Werkzeug>=2.3.0
Requires-Dist: Jinja2>=3.1.0
Requires-Dist: WTForms>=3.0.0
Provides-Extra: dev
Requires-Dist: pytest>=7.0.0; extra == "dev"
Requires-Dist: pytest-cov>=4.0.0; extra == "dev"
Requires-Dist: black>=22.0.0; extra == "dev"
Requires-Dist: flake8>=5.0.0; extra == "dev"
Requires-Dist: mypy>=1.0.0; extra == "dev"
Requires-Dist: sphinx>=5.0.0; extra == "dev"
Dynamic: author
Dynamic: home-page
Dynamic: license-file
Dynamic: requires-python
